cdp_scrapers/README.md
cdp_scrapers/__init__.py
cdp_scrapers/finding_legistar_id.md
cdp_scrapers/legistar_content_parsers.py
cdp_scrapers/legistar_utils.py
cdp_scrapers/prime_gov_utils.py
cdp_scrapers/py.typed
cdp_scrapers/scraper_utils.py
cdp_scrapers/static_data.md
cdp_scrapers/types.py
cdp_scrapers/youtube_utils.py
cdp_scrapers/instances/__init__.py
cdp_scrapers/instances/atlanta.py
cdp_scrapers/instances/empty.py
cdp_scrapers/instances/houston.py
cdp_scrapers/instances/kingcounty-static.json
cdp_scrapers/instances/kingcounty.py
cdp_scrapers/instances/lacity.py
cdp_scrapers/instances/portland-static.json
cdp_scrapers/instances/portland.py
cdp_scrapers/instances/seattle-static.json
cdp_scrapers/instances/seattle.py
cdp_scrapers/tests/legistar_content_parser_test.py
cdp_scrapers/tests/test_prime_gov_agenda_scraper.py
cdp_scrapers/tests/test_prime_gov_utils.py
cdp_scrapers/tests/test_scraper_utils.py
cdp_scrapers/tests/test_scrapers.py
cdp_scrapers/tests/test_youtube_scraper.py
docs/Makefile
docs/conf.py
docs/contributing.rst
docs/finding_legistar_id.rst
docs/index.rst
docs/installation.rst
docs/legistar_scraper.rst
docs/make.bat
docs/modules.rst
images/get_events.png
images/seattle_legistar_url.png
cdp_scrapers-0.8.1.dist-info/LICENSE
cdp_scrapers-0.8.1.dist-info/METADATA
cdp_scrapers-0.8.1.dist-info/WHEEL
cdp_scrapers-0.8.1.dist-info/top_level.txt
cdp_scrapers-0.8.1.dist-info/RECORD
