Metadata-Version: 2.1
Name: cdp-scrapers
Version: 0.8.1
Summary: Scratchpad for scraper development and general utilities.
Author: Sung Cho, Shak Ragoler
Author-email: Eva Maxfield Brown <evamaxfieldbrown@gmail.com>
License: MIT License
Project-URL: Homepage, https://github.com/CouncilDataProject/cdp-scrapers
Project-URL: Bug Tracker, https://github.com/CouncilDataProject/cdp-scrapers/issues
Project-URL: Documentation, https://CouncilDataProject.github.io/cdp-scrapers
Project-URL: User Support, https://github.com/CouncilDataProject/cdp-scrapers/issues
Classifier: Development Status :: 4 - Beta
Classifier: Natural Language :: English
Classifier: Programming Language :: Python :: 3.8
Classifier: Programming Language :: Python :: 3.9
Classifier: Programming Language :: Python :: 3.10
Classifier: Programming Language :: Python :: 3.11
Requires-Python: >=3.8
License-File: LICENSE
Requires-Dist: beautifulsoup4~=4.9
Requires-Dist: cdp-backend>=3.2.4
Requires-Dist: defusedxml~=0.7.1
Requires-Dist: pytz~=2021.1
Requires-Dist: requests~=2.25
Requires-Dist: clean-text~=0.6.0
Requires-Dist: civic-scraper~=0.2.5
Requires-Dist: yt-dlp>=2023.2.17
Provides-Extra: atlanta
Requires-Dist: selenium~=4.3; extra == "atlanta"
Requires-Dist: webdriver-manager~=3.8; extra == "atlanta"
Provides-Extra: all
Requires-Dist: selenium~=4.3; extra == "all"
Requires-Dist: webdriver-manager~=3.8; extra == "all"
Provides-Extra: lint
Requires-Dist: black>=22.3.0; extra == "lint"
Requires-Dist: check-manifest>=0.48; extra == "lint"
Requires-Dist: ruff>=0.0.216; extra == "lint"
Requires-Dist: mypy>=0.790; extra == "lint"
Requires-Dist: pre-commit>=2.20.0; extra == "lint"
Provides-Extra: test
Requires-Dist: coverage>=5.1; extra == "test"
Requires-Dist: pytest>=5.4.3; extra == "test"
Requires-Dist: pytest-cov>=2.9.0; extra == "test"
Requires-Dist: pytest-raises>=0.11; extra == "test"
Requires-Dist: pytest-rerunfailures>=11.1.2; extra == "test"
Provides-Extra: docs
Requires-Dist: m2r2>=0.2.7; extra == "docs"
Requires-Dist: Sphinx>=4.0.0; extra == "docs"
Requires-Dist: furo>=2022.4.7; extra == "docs"
Requires-Dist: numpydoc; extra == "docs"
Requires-Dist: sphinx-copybutton; extra == "docs"
Requires-Dist: docutils<0.19,>=0.18; extra == "docs"
Provides-Extra: dev
Requires-Dist: ipython>=8.4.0; extra == "dev"
